{
  "name": "@siberiacancode/eslint",
  "entries": [
    {
      "date": "Mon, 18 Nov 2024 16:04:46 GMT",
      "version": "2.4.0",
      "tag": "@siberiacancode/eslint_v2.4.0",
      "comments": {
        "minor": [
          {
            "author": "dmitriybabinup@gmail.com",
            "package": "@siberiacancode/eslint",
            "commit": "not available",
            "comment": "release/eslint/2.4.0 🧊 update eslint and fetches"
          }
        ]
      }
    },
    {
      "date": "Sat, 02 Nov 2024 15:33:48 GMT",
      "version": "2.3.0",
      "tag": "@siberiacancode/eslint_v2.3.0",
      "comments": {
        "minor": [
          {
            "author": "dmitriybabinup@gmail.com",
            "package": "@siberiacancode/eslint",
            "commit": "not available",
            "comment": "release/eslint/2.3.0 🧊 add next, update versions"
          }
        ]
      }
    },
    {
      "date": "Thu, 31 Oct 2024 05:26:12 GMT",
      "version": "2.2.0",
      "tag": "@siberiacancode/eslint_v2.2.0",
      "comments": {
        "none": [
          {
            "author": "dmitriybabinup@gmail.com",
            "package": "@siberiacancode/eslint",
            "commit": "not available",
            "comment": "fetches 🧊 init package"
          }
        ]
      }
    },
    {
      "date": "Sun, 18 Aug 2024 10:08:49 GMT",
      "version": "2.2.0",
      "tag": "@siberiacancode/eslint_v2.2.0",
      "comments": {
        "minor": [
          {
            "author": "dmitriybabinup@gmail.com",
            "package": "@siberiacancode/eslint",
            "commit": "not available",
            "comment": "?? release/eslint/2.2.0"
          }
        ]
      }
    },
    {
      "date": "Thu, 15 Aug 2024 10:32:35 GMT",
      "version": "2.1.0",
      "tag": "@siberiacancode/eslint_v2.1.0",
      "comments": {
        "minor": [
          {
            "author": "dmitriybabinup@gmail.com",
            "package": "@siberiacancode/eslint",
            "commit": "not available",
            "comment": "?? release/eslint/2.1.0"
          }
        ]
      }
    },
    {
      "date": "Thu, 15 Aug 2024 10:17:05 GMT",
      "version": "2.0.7",
      "tag": "@siberiacancode/eslint_v2.0.7",
      "comments": {
        "patch": [
          {
            "author": "dmitriybabinup@gmail.com",
            "package": "@siberiacancode/eslint",
            "commit": "not available",
            "comment": "?? release/eslint/2.1.0"
          }
        ]
      }
    },
    {
      "date": "Wed, 14 Aug 2024 14:06:21 GMT",
      "version": "2.0.6",
      "tag": "@siberiacancode/eslint_v2.0.6",
      "comments": {
        "patch": [
          {
            "author": "dmitriybabinup@gmail.com",
            "package": "@siberiacancode/eslint",
            "commit": "not available",
            "comment": "?? release/eslint/2.0.6"
          }
        ]
      }
    },
    {
      "date": "Wed, 14 Aug 2024 10:16:39 GMT",
      "version": "2.0.5",
      "tag": "@siberiacancode/eslint_v2.0.5",
      "comments": {
        "patch": [
          {
            "author": "dmitriybabinup@gmail.com",
            "package": "@siberiacancode/eslint",
            "commit": "not available",
            "comment": "?? release/eslint/2.0.5"
          }
        ]
      }
    },
    {
      "date": "Tue, 13 Aug 2024 13:57:21 GMT",
      "version": "2.0.4",
      "tag": "@siberiacancode/eslint_v2.0.4",
      "comments": {
        "patch": [
          {
            "author": "dmitriybabinup@gmail.com",
            "package": "@siberiacancode/eslint",
            "commit": "not available",
            "comment": "?? release/eslint/2.0.4"
          }
        ]
      }
    },
    {
      "date": "Tue, 13 Aug 2024 13:42:51 GMT",
      "version": "2.0.3",
      "tag": "@siberiacancode/eslint_v2.0.3",
      "comments": {
        "patch": [
          {
            "author": "dmitriybabinup@gmail.com",
            "package": "@siberiacancode/eslint",
            "commit": "not available",
            "comment": "?? release/eslint/2.0.3"
          }
        ]
      }
    },
    {
      "date": "Tue, 13 Aug 2024 13:40:15 GMT",
      "version": "2.0.2",
      "tag": "@siberiacancode/eslint_v2.0.2",
      "comments": {
        "patch": [
          {
            "author": "dmitriybabinup@gmail.com",
            "package": "@siberiacancode/eslint",
            "commit": "not available",
            "comment": "?? release/eslint/2.0.2"
          }
        ]
      }
    },
    {
      "date": "Tue, 13 Aug 2024 11:55:42 GMT",
      "version": "2.0.1",
      "tag": "@siberiacancode/eslint_v2.0.1",
      "comments": {
        "patch": [
          {
            "author": "dmitriybabinup@gmail.com",
            "package": "@siberiacancode/eslint",
            "commit": "not available",
            "comment": "🎉 release/eslint/2.0.1"
          }
        ]
      }
    },
    {
      "date": "Tue, 13 Aug 2024 11:33:57 GMT",
      "version": "2.0.0",
      "tag": "@siberiacancode/eslint_v2.0.0",
      "comments": {
        "major": [
          {
            "author": "dmitriybabinup@gmail.com",
            "package": "@siberiacancode/eslint",
            "commit": "not available",
            "comment": "?? release/eslint/2.0.0"
          }
        ]
      }
    },
    {
      "date": "Sat, 01 Jun 2024 17:41:20 GMT",
      "version": "1.1.1",
      "tag": "@siberiacancode/eslint_v1.1.1",
      "comments": {
        "patch": [
          {
            "author": "dmitriybabinup@gmail.com",
            "package": "@siberiacancode/eslint",
            "commit": "not available",
            "comment": ""
          }
        ]
      }
    },
    {
      "date": "Fri, 16 Feb 2024 11:19:32 GMT",
      "version": "1.1.0",
      "tag": "@siberiacancode/eslint_v1.1.0",
      "comments": {
        "minor": [
          {
            "author": "dmitriybabinup@gmail.com",
            "package": "@siberiacancode/eslint",
            "commit": "not available",
            "comment": "🧊 update packages"
          }
        ]
      }
    },
    {
      "date": "Mon, 02 Oct 2023 17:31:56 GMT",
      "version": "1.0.3",
      "tag": "@siberiacancode/eslint_v1.0.3",
      "comments": {
        "patch": [
          {
            "author": "dmitriybabinup@gmail.com",
            "package": "@siberiacancode/eslint",
            "commit": "not available",
            "comment": {
              "title": ""
            }
          }
        ]
      }
    },
    {
      "date": "Fri, 22 Sep 2023 18:24:59 GMT",
      "version": "1.0.2",
      "tag": "@siberiacancode/eslint_v1.0.2",
      "comments": {
        "patch": [
          {
            "author": "dmitriybabinup@gmail.com",
            "package": "@siberiacancode/eslint",
            "commit": "not available",
            "comment": "☄ update versions"
          }
        ]
      }
    },
    {
      "date": "Sat, 16 Sep 2023 11:31:08 GMT",
      "version": "1.0.1",
      "tag": "@siberiacancode/eslint_v1.0.1",
      "comments": {
        "patch": [
          {
            "author": "dmitriybabinup@gmail.com",
            "package": "@siberiacancode/eslint",
            "commit": "not available",
            "comment": "🎉 change import rules"
          }
        ]
      }
    },
    {
      "date": "Tue, 12 Sep 2023 07:53:07 GMT",
      "version": "1.0.0",
      "tag": "@siberiacancode/eslint_v1.0.0",
      "comments": {
        "major": [
          {
            "author": "dmitriybabinup@gmail.com",
            "package": "@siberiacancode/eslint",
            "commit": "not available",
            "comment": {
              "title": ""
            }
          }
        ]
      }
    }
  ]
}
